lefaire/__init__.py
lefaire/connect.py
lefaire/data.py
lefaire/main.py
lefaire/prompt.py
lefaire/view.py
lefaire-0.1.8.dist-info/METADATA
lefaire-0.1.8.dist-info/WHEEL
lefaire-0.1.8.dist-info/entry_points.txt
lefaire-0.1.8.dist-info/RECORD
