Metadata-Version: 2.1
Name: lefaire
Version: 0.1.8
Summary: 
Author: okcedric
Author-email: contact@okcedric.com
Requires-Python: >=3.10,<4.0
Classifier: Programming Language :: Python :: 3
Classifier: Programming Language :: Python :: 3.10
Classifier: Programming Language :: Python :: 3.11
Classifier: Programming Language :: Python :: 3.12
Classifier: Programming Language :: Python :: 3.13
Requires-Dist: colorama (>=0.4.6,<0.5.0)
Requires-Dist: mariadb (>=1.1.11,<2.0.0)
Requires-Dist: packaging (>=24.2,<25.0)
Requires-Dist: python-dotenv (>=1.0.1,<2.0.0)
Requires-Dist: typer (>=0.15.1,<0.16.0)
